drresult/__init__.py
drresult/class_decorators.py
drresult/function_decorators.py
drresult/gather_result.py
drresult/logging.py
drresult/option.py
drresult/result.py
drresult-0.6.5.dist-info/LICENSE
drresult-0.6.5.dist-info/METADATA
drresult-0.6.5.dist-info/WHEEL
drresult-0.6.5.dist-info/RECORD
