Metadata-Version: 2.1
Name: DrResult
Version: 0.6.5
Summary: 
License: MIT
Author: Ole Kliemann
Author-email: mail@olekliemann.de
Requires-Python: >=3.12
Classifier: License :: OSI Approved :: MIT License
Classifier: Programming Language :: Python :: 3
Classifier: Programming Language :: Python :: 3.12
Classifier: Programming Language :: Python :: 3.13
